buildman/README.rst
buildman/__init__.py
buildman/board.py
buildman/boards.py
buildman/bsettings.py
buildman/builder.py
buildman/builderthread.py
buildman/buildman.rst
buildman/cfgutil.py
buildman/cmdline.py
buildman/control.py
buildman/kconfiglib.py
buildman/main.py
buildman/toolchain.py
buildman-0.0.7.dist-info/licenses/LICENSE
buildman-0.0.7.dist-info/METADATA
buildman-0.0.7.dist-info/WHEEL
buildman-0.0.7.dist-info/entry_points.txt
buildman-0.0.7.dist-info/top_level.txt
buildman-0.0.7.dist-info/RECORD
