Metadata-Version: 2.4
Name: buildman
Version: 0.0.7
Summary: Buildman build tool for U-Boot
Author-email: Simon Glass <sjg@chromium.org>
Project-URL: Homepage, https://docs.u-boot.org/en/latest/build/buildman.html
Project-URL: Bug Tracker, https://source.denx.de/groups/u-boot/-/issues
Classifier: Programming Language :: Python :: 3
Classifier: License :: OSI Approved :: GNU General Public License v2 or later (GPLv2+)
Classifier: Operating System :: OS Independent
Requires-Python: >=3.7
License-File: LICENSE
Requires-Dist: filelock>=3.0.12
Requires-Dist: u_boot_pylib>=0.0.6
Requires-Dist: patch-manager>=0.0.6
Dynamic: license-file
